xo2/__init__.py
xo2/app.py
xo2/render.py
xo2-0.1.0.dist-info/LICENSE
xo2-0.1.0.dist-info/WHEEL
xo2-0.1.0.dist-info/METADATA
xo2-0.1.0.dist-info/RECORD
