Metadata-Version: 2.1
Name: xo2
Version: 0.1.0
Summary: EAF-based 3D engine
Home-page: https://github.com/pkulev/xo2
License: MIT
Keywords: pygame,sdl2,application,framework
Author: Pavel Kulyov
Author-email: kulyov.pavel@gmail.com
Requires-Python: >=3.7,<4.0
Classifier: Development Status :: 3 - Alpha
Classifier: Intended Audience :: Developers
Classifier: License :: OSI Approved :: MIT License
Classifier: Operating System :: POSIX :: Linux
Classifier: Programming Language :: Python :: 3
Classifier: Programming Language :: Python :: 3.7
Classifier: Programming Language :: Python :: 3.8
Classifier: Programming Language :: Python :: 3.9
Requires-Dist: eaf (>=0.2.2,<0.3.0)
Project-URL: Repository, https://github.com/pkulev/xo2
